{"data":{"threaded_conversation_with_injections_v2":{"instructions":[{"type":"TimelineAddEntries","entries":[{"entryId":"label-7296581335582793482","sortIndex":"7296581335582793482","content":{"entryType":"TimelineTimelineItem","__typename":"TimelineTimelineItem","itemContent":{"itemType":"TimelineLabel","__typename":"TimelineLabel","text":"Probable spam","display_type":"InlineHeader"}}},{"entryId":"conversationthread-1926794917075964256","sortIndex":"7296581335582793477","content":{"entryType":"TimelineTimelineModule","__typename":"TimelineTimelineModule","items":[{"entryId":"conversationthread-1926794917075964256-tweet-1926794917075964256","item":{"itemContent":{"itemType":"TimelineTweet","__typename":"TimelineTweet","tweet_results":{"result":{"__typename":"Tweet","rest_id":"1926794917075964256","has_birdwatch_notes":false,"core":{"user_results":{"result":{"__typename":"User","id":"VXNlcjoxOTEyOTAxMzU5MTg1MDg0NDE2","rest_id":"1912901359185084416","affiliates_highlighted_label":{},"has_graduated_access":true,"is_blue_verified":false,"legacy":{"can_dm":false,"can_media_tag":true,"created_at":"Thu Apr 17 16:10:09 +0000 2025","default_profile":true,"default_profile_image":false,"description":"A next-gen geo-tagged playground where players meet opportunities offered with a timeless technology. Map-based gameplay with capabilities to engage playe","entities":{"description":{"urls":[]}},"fast_followers_count":0,"favourites_count":11,"followers_count":3,"friends_count":5,"has_custom_timelines":false,"is_translator":false,"listed_count":0,"location":"Serbia","media_count":0,"name":"Athena Vincent","normal_followers_count":3,"pinned_tweet_ids_str":[],"possibly_sensitive":false,"profile_banner_url":"https://pbs.twimg.com/profile_banners/1912901359185084416/1746824949","profile_image_url_https":"https://pbs.twimg.com/profile_images/1920949168043962368/4limWbRF_normal.jpg","profile_interstitial_type":"","screen_name":"VincentAthwor","statuses_count":69,"translator_type":"none","verified":false,"want_retweets":false,"withheld_in_countries":[]},"smart_blocked_by":false,"smart_blocking":false,"business_account":{}}}},"unmention_data":{},"edit_control":{"edit_tweet_ids":["1926794917075964256"],"editable_until_msecs":"1748222281000","is_edit_eligible":false,"edits_remaining":"5"},"is_translatable":false,"views":{"count":"16","state":"EnabledWithCount"},"source":"<a href=\"https://mobile.twitter.com\" rel=\"nofollow\">Twitter Web App</a>","legacy":{"created_at":"Mon May 26 00:18:01 +0000 2025","conversation_id_str":"1926790701271982290","display_text_range":[11,76],"entities":{"user_mentions":[{"id_str":"48111864","name":"Alec Stapp","screen_name":"AlecStapp","indices":[0,10]},{"id_str":"2176913191","name":"Burke","screen_name":"adviceBurke","indices":[27,39]}],"urls":[],"hashtags":[],"symbols":[]},"favorite_count":1,"favorited":false,"full_text":"@AlecStapp He is my savior\n@adviceBurke\nEveryone should follow him 💎 🔥 🌻 🎌 💎","in_reply_to_screen_name":"AlecStapp","in_reply_to_status_id_str":"1926790701271982290","in_reply_to_user_id_str":"48111864","is_quote_status":false,"lang":"en","quote_count":0,"reply_count":0,"retweet_count":0,"retweeted":false,"user_id_str":"1912901359185084416","id_str":"1926794917075964256"},"quick_promote_eligibility":{"eligibility":"IneligibleNotProfessional"}}},"tweetDisplayType":"Tweet"},"clientEventInfo":{"component":"tweet","element":"tweet","details":{"conversationDetails":{"conversationSection":"LowQuality"},"timelinesDetails":{"controllerData":"DAACDAAEDAABCgABFICKiCAHAAUKAAIAAAAABACASAAAAAA="}}}}}],"displayType":"VerticalConversation","clientEventInfo":{"component":"tweet","element":"tweet","details":{"conversationDetails":{"conversationSection":"LowQuality"}}}}},{"entryId":"conversationthread-1924484264961118443-55f971852347d53","sortIndex":"7296581335582793467","content":{"entryType":"TimelineTimelineModule","__typename":"TimelineTimelineModule","items":[{"entryId":"conversationthread-1924484264961118443-tweet-1924484264961118443-55f971852347d53","item":{"itemContent":{"itemType":"TimelineTweet","__typename":"TimelineTweet","tweet_results":{"result":{"__typename":"Tweet","rest_id":"1924484264961118443","has_birdwatch_notes":false,"core":{"user_results":{"result":{"__typename":"User","id":"VXNlcjoxMzk5MTQ4NTYz","rest_id":"1399148563","affiliates_highlighted_label":{},"has_graduated_access":true,"is_blue_verified":true,"legacy":{"can_dm":false,"can_media_tag":true,"created_at":"Fri May 03 08:03:21 +0000 2013","default_profile":false,"default_profile_image":false,"description":"Kraken is your bridge to the world of crypto. Spot, Futures, Margin, Staking & OTC. Buy, sell, trade, earn, explore and learn Need help? @krakensupport 👈","entities":{"description":{"urls":[]},"url":{"urls":[{"display_url":"kraken.com","expanded_url":"https://kraken.com","url":"https://t.co/1Vim26q40l","indices":[0,23]}]}},"fast_followers_count":0,"favourites_count":10214,"followers_count":1670128,"friends_count":63,"has_custom_timelines":false,"is_translator":false,"listed_count":10210,"location":"Financial Freedom","media_count":6102,"name":"Kraken Exchange","normal_followers_count":1670128,"pinned_tweet_ids_str":["1925578761212150007"],"possibly_sensitive":false,"profile_banner_url":"https://pbs.twimg.com/profile_banners/1399148563/1745500345","profile_image_url_https":"https://pbs.twimg.com/profile_images/1871200667974488064/B1F4l2qM_normal.jpg","profile_interstitial_type":"","screen_name":"krakenfx","statuses_count":26456,"translator_type":"regular","url":"https://t.co/1Vim26q40l","verified":false,"verified_type":"Business","want_retweets":false,"withheld_in_countries":[]},"professional":{"rest_id":"1590930925465923584","professional_type":"Business","category":[{"id":192,"name":"Financial Services","icon_name":"IconBriefcaseStroke"}]},"smart_blocked_by":false,"smart_blocking":false,"business_account":{"affiliates_count":27}}}},"unmention_data":{},"edit_control":{"edit_tweet_ids":["1924484264961118443"],"editable_until_msecs":"1747671378000","is_edit_eligible":true,"edits_remaining":"5"},"is_translatable":false,"views":{"count":"127196","state":"EnabledWithCount"},"source":"<a href=\"https://www.sprinklr.com\" rel=\"nofollow\">Sprinklr</a>","legacy":{"created_at":"Mon May 19 15:16:18 +0000 2025","conversation_id_str":"1924484264961118443","display_text_range":[0,203],"entities":{"media":[{"display_url":"pic.x.com/G4GdpSFGBX","expanded_url":"https://x.com/krakenfx/status/1924484264961118443/photo/1","id_str":"1924484259261100032","indices":[204,227],"media_key":"3_1924484259261100032","media_url_https":"https://pbs.twimg.com/media/GrUkPMkWsAAt6XS.png","type":"photo","url":"https://t.co/G4GdpSFGBX","ext_media_availability":{"status":"Available"},"features":{"large":{"faces":[]},"medium":{"faces":[]},"small":{"faces":[]},"orig":{"faces":[]}},"sizes":{"large":{"h":1152,"w":2048,"resize":"fit"},"medium":{"h":675,"w":1200,"resize":"fit"},"small":{"h":383,"w":680,"resize":"fit"},"thumb":{"h":150,"w":150,"resize":"crop"}},"original_info":{"height":2160,"width":3840,"focus_rects":[{"x":0,"y":0,"w":3840,"h":2150},{"x":1680,"y":0,"w":2160,"h":2160},{"x":1945,"y":0,"w":1895,"h":2160},{"x":2760,"y":0,"w":1080,"h":2160},{"x":0,"y":0,"w":3840,"h":2160}]}}],"user_mentions":[{"id_str":"1855363480859320320","name":"clanker","screen_name":"clankeronbase","indices":[11,25]}],"urls":[{"display_url":"p.k.xyz/9f1e/2xhplv5c","expanded_url":"https://p.k.xyz/9f1e/2xhplv5c","url":"https://t.co/ABqhYHxlzJ","indices":[147,170]}],"hashtags":[],"symbols":[]},"extended_entities":{"media":[{"display_url":"pic.x.com/G4GdpSFGBX","expanded_url":"https://x.com/krakenfx/status/1924484264961118443/photo/1","id_str":"1924484259261100032","indices":[204,227],"media_key":"3_1924484259261100032","media_url_https":"https://pbs.twimg.com/media/GrUkPMkWsAAt6XS.png","type":"photo","url":"https://t.co/G4GdpSFGBX","ext_media_availability":{"status":"Available"},"features":{"large":{"faces":[]},"medium":{"faces":[]},"small":{"faces":[]},"orig":{"faces":[]}},"sizes":{"large":{"h":1152,"w":2048,"resize":"fit"},"medium":{"h":675,"w":1200,"resize":"fit"},"small":{"h":383,"w":680,"resize":"fit"},"thumb":{"h":150,"w":150,"resize":"crop"}},"original_info":{"height":2160,"width":3840,"focus_rects":[{"x":0,"y":0,"w":3840,"h":2150},{"x":1680,"y":0,"w":2160,"h":2160},{"x":1945,"y":0,"w":1895,"h":2160},{"x":2760,"y":0,"w":1080,"h":2160},{"x":0,"y":0,"w":3840,"h":2160}]}}]},"favorite_count":308,"favorited":false,"full_text":"🔊 $CLANKER @clankeronbase is now available for trading on Kraken! \n\n✔️ Deposits and withdrawals are enabled\n\n🎉 Trading is now live!\n\nTrade here ⤵️\nhttps://t.co/ABqhYHxlzJ \n\n*Geographic restrictions apply https://t.co/G4GdpSFGBX","is_quote_status":false,"lang":"en","possibly_sensitive":false,"possibly_sensitive_editable":true,"quote_count":11,"reply_count":106,"retweet_count":62,"retweeted":false,"user_id_str":"1399148563","id_str":"1924484264961118443"},"quick_promote_eligibility":{"eligibility":"IneligibleNotProfessional"}}},"tweetDisplayType":"Tweet","promotedMetadata":{"advertiser_results":{"result":{"__typename":"User","id":"VXNlcjoxMzk5MTQ4NTYz","rest_id":"1399148563","affiliates_highlighted_label":{},"has_graduated_access":true,"is_blue_verified":true,"legacy":{"can_dm":false,"can_media_tag":true,"created_at":"Fri May 03 08:03:21 +0000 2013","default_profile":false,"default_profile_image":false,"description":"Kraken is your bridge to the world of crypto. Spot, Futures, Margin, Staking & OTC. Buy, sell, trade, earn, explore and learn Need help? @krakensupport 👈","entities":{"description":{"urls":[]},"url":{"urls":[{"display_url":"kraken.com","expanded_url":"https://kraken.com","url":"https://t.co/1Vim26q40l","indices":[0,23]}]}},"fast_followers_count":0,"favourites_count":10214,"followers_count":1670128,"friends_count":63,"has_custom_timelines":false,"is_translator":false,"listed_count":10210,"location":"Financial Freedom","media_count":6102,"name":"Kraken Exchange","normal_followers_count":1670128,"pinned_tweet_ids_str":["1925578761212150007"],"possibly_sensitive":false,"profile_banner_url":"https://pbs.twimg.com/profile_banners/1399148563/1745500345","profile_image_url_https":"https://pbs.twimg.com/profile_images/1871200667974488064/B1F4l2qM_normal.jpg","profile_interstitial_type":"","screen_name":"krakenfx","statuses_count":26456,"translator_type":"regular","url":"https://t.co/1Vim26q40l","verified":false,"verified_type":"Business","want_retweets":false,"withheld_in_countries":[]},"professional":{"rest_id":"1590930925465923584","professional_type":"Business","category":[{"id":192,"name":"Financial Services","icon_name":"IconBriefcaseStroke"}]},"smart_blocked_by":false,"smart_blocking":false,"business_account":{"affiliates_count":27}}},"disclosureType":"NoDisclosure","experimentValues":[],"impressionId":"55f971852347d53","impressionString":"55f971852347d53","clickTrackingInfo":{"urlParams":[{"key":"twclid","value":"2-an70m3t6f8oy286aad3397gi"}]}}},"clientEventInfo":{"component":"tweet","element":"tweet","details":{"conversationDetails":{"conversationSection":"LowQuality"}}}}}],"displayType":"VerticalConversation","clientEventInfo":{"component":"tweet","element":"tweet","details":{"conversationDetails":{"conversationSection":"LowQuality"}}}}},{"entryId":"conversationthread-1926794165527990547","sortIndex":"7296581335582793457","content":{"entryType":"TimelineTimelineModule","__typename":"TimelineTimelineModule","items":[{"entryId":"conversationthread-1926794165527990547-tweet-1926794165527990547","item":{"itemContent":{"itemType":"TimelineTweet","__typename":"TimelineTweet","tweet_results":{"result":{"__typename":"Tweet","rest_id":"1926794165527990547","has_birdwatch_notes":false,"core":{"user_results":{"result":{"__typename":"User","id":"VXNlcjoxOTE0NTE4NDE0MjIxMjQ2NDY0","rest_id":"1914518414221246464","affiliates_highlighted_label":{},"has_graduated_access":true,"is_blue_verified":false,"legacy":{"can_dm":false,"can_media_tag":true,"created_at":"Tue Apr 22 03:15:44 +0000 2025","default_profile":true,"default_profile_image":false,"description":"@doubletop_io Team\n@zkLend Support Team\n@myBraavos Lead\n@CarmineOptions CM","entities":{"description":{"urls":[]}},"fast_followers_count":0,"favourites_count":213,"followers_count":6,"friends_count":5,"has_custom_timelines":false,"is_translator":false,"listed_count":0,"location":"Daytona Beach","media_count":0,"name":"Samantha Lake","normal_followers_count":6,"pinned_tweet_ids_str":[],"possibly_sensitive":false,"profile_banner_url":"https://pbs.twimg.com/profile_banners/1914518414221246464/1746968149","profile_image_url_https":"https://pbs.twimg.com/profile_images/1921549788849283072/ggm3jd0H_normal.jpg","profile_interstitial_type":"","screen_name":"lake_samanSh","statuses_count":129,"translator_type":"none","verified":false,"want_retweets":false,"withheld_in_countries":[]},"smart_blocked_by":false,"smart_blocking":false,"business_account":{}}}},"unmention_data":{},"edit_control":{"edit_tweet_ids":["1926794165527990547"],"editable_until_msecs":"1748222101000","is_edit_eligible":false,"edits_remaining":"5"},"is_translatable":false,"views":{"count":"12","state":"EnabledWithCount"},"source":"<a href=\"https://mobile.twitter.com\" rel=\"nofollow\">Twitter Web App</a>","legacy":{"created_at":"Mon May 26 00:15:01 +0000 2025","conversation_id_str":"1926790701271982290","display_text_range":[11,64],"entities":{"user_mentions":[{"id_str":"48111864","name":"Alec Stapp","screen_name":"AlecStapp","indices":[0,10]},{"id_str":"1640700474","name":"Maverik -Stock Analyst","screen_name":"Weijueye_888","indices":[43,56]}],"urls":[],"hashtags":[],"symbols":[]},"favorite_count":4,"favorited":false,"full_text":"@AlecStapp This gentleman is really great.\n@Weijueye_888 🌂 🍂 🎉 🌟","in_reply_to_screen_name":"AlecStapp","in_reply_to_status_id_str":"1926790701271982290","in_reply_to_user_id_str":"48111864","is_quote_status":false,"lang":"en","quote_count":0,"reply_count":0,"retweet_count":0,"retweeted":false,"user_id_str":"1914518414221246464","id_str":"1926794165527990547"},"quick_promote_eligibility":{"eligibility":"IneligibleNotProfessional"}}},"tweetDisplayType":"Tweet"},"clientEventInfo":{"component":"tweet","element":"tweet","details":{"conversationDetails":{"conversationSection":"LowQuality"},"timelinesDetails":{"controllerData":"DAACDAAEDAABCgABFQCKiCQDAAUKAAIAAAAABQCASAAAAAA="}}}}}],"displayType":"VerticalConversation","clientEventInfo":{"component":"tweet","element":"tweet","details":{"conversationDetails":{"conversationSection":"LowQuality"}}}}},{"entryId":"conversationthread-1926790783815868550","sortIndex":"7296581335582793447","content":{"entryType":"TimelineTimelineModule","__typename":"TimelineTimelineModule","items":[{"entryId":"conversationthread-1926790783815868550-tweet-1926790783815868550","item":{"itemContent":{"itemType":"TimelineTweet","__typename":"TimelineTweet","tweet_results":{"result":{"__typename":"Tweet","rest_id":"1926790783815868550","has_birdwatch_notes":false,"core":{"user_results":{"result":{"__typename":"User","id":"VXNlcjoxOTEwNjExOTQwMDEyODU1Mjk2","rest_id":"1910611940012855296","affiliates_highlighted_label":{},"has_graduated_access":true,"is_blue_verified":false,"legacy":{"can_dm":false,"can_media_tag":true,"created_at":"Fri Apr 11 08:33:13 +0000 2025","default_profile":true,"default_profile_image":false,"description":"ar out item within. Bad according clearly. Start sign fa","entities":{"description":{"urls":[]},"url":{"urls":[{"display_url":"dribbble.com/shane13","expanded_url":"https://dribbble.com/shane13","url":"https://t.co/HzNBF5oJty","indices":[0,23]}]}},"fast_followers_count":0,"favourites_count":0,"followers_count":0,"friends_count":0,"has_custom_timelines":false,"is_translator":false,"listed_count":0,"location":"Leawood","media_count":0,"name":"Aliabbas Eraslan","normal_followers_count":0,"pinned_tweet_ids_str":[],"possibly_sensitive":false,"profile_banner_url":"https://pbs.twimg.com/profile_banners/1910611940012855296/1746112537","profile_image_url_https":"https://pbs.twimg.com/profile_images/1917949439555072000/lRx_DpLt_normal.jpg","profile_interstitial_type":"","screen_name":"AliabbasEr25200","statuses_count":5,"translator_type":"none","url":"https://t.co/HzNBF5oJty","verified":false,"want_retweets":false,"withheld_in_countries":[]},"smart_blocked_by":false,"smart_blocking":false,"business_account":{}}}},"unmention_data":{},"edit_control":{"edit_tweet_ids":["1926790783815868550"],"editable_until_msecs":"1748221295000","is_edit_eligible":false,"edits_remaining":"5"},"is_translatable":false,"views":{"count":"19","state":"EnabledWithCount"},"source":"<a href=\"http://twitter.com/download/iphone\" rel=\"nofollow\">Twitter for iPhone</a>","legacy":{"created_at":"Mon May 26 00:01:35 +0000 2025","conversation_id_str":"1926790701271982290","display_text_range":[11,77],"entities":{"user_mentions":[{"id_str":"48111864","name":"Alec Stapp","screen_name":"AlecStapp","indices":[0,10]},{"id_str":"1560480146","name":"Owen","screen_name":"Adityafajarkus2","indices":[32,48]}],"urls":[],"hashtags":[],"symbols":[]},"favorite_count":0,"favorited":false,"full_text":"@AlecStapp This guy is awesome👍\n@Adityafajarkus2🇺🇸\nEveryone should follow him","in_reply_to_screen_name":"AlecStapp","in_reply_to_status_id_str":"1926790701271982290","in_reply_to_user_id_str":"48111864","is_quote_status":false,"lang":"en","quote_count":0,"reply_count":0,"retweet_count":0,"retweeted":false,"user_id_str":"1910611940012855296","id_str":"1926790783815868550"},"quick_promote_eligibility":{"eligibility":"IneligibleNotProfessional"}}},"tweetDisplayType":"Tweet"},"clientEventInfo":{"component":"tweet","element":"tweet","details":{"conversationDetails":{"conversationSection":"LowQuality"},"timelinesDetails":{"controllerData":"DAACDAAEDAABCgABFID6iCgDAAUKAAIAAAAABQCASAAAAAA="}}}}}],"displayType":"VerticalConversation","clientEventInfo":{"component":"tweet","element":"tweet","details":{"conversationDetails":{"conversationSection":"LowQuality"}}}}},{"entryId":"conversationthread-1926800646226784509","sortIndex":"7296581335582793437","content":{"entryType":"TimelineTimelineModule","__typename":"TimelineTimelineModule","items":[{"entryId":"conversationthread-1926800646226784509-tweet-1926800646226784509","item":{"itemContent":{"itemType":"TimelineTweet","__typename":"TimelineTweet","tweet_results":{"result":{"__typename":"Tweet","rest_id":"1926800646226784509","has_birdwatch_notes":false,"core":{"user_results":{"result":{"__typename":"User","id":"VXNlcjoxOTA5Mjc0MjM2NzU5NTA2OTQ0","rest_id":"1909274236759506944","affiliates_highlighted_label":{},"has_graduated_access":true,"is_blue_verified":false,"legacy":{"can_dm":false,"can_media_tag":true,"created_at":"Mon Apr 07 15:57:39 +0000 2025","default_profile":true,"default_profile_image":false,"description":"Animal away source character cover west somebody. Everything","entities":{"description":{"urls":[]},"url":{"urls":[{"display_url":"join.skype.com/invite/evansch…","expanded_url":"https://join.skype.com/invite/evanscharles","url":"https://t.co/I70fRK6vA5","indices":[0,23]}]}},"fast_followers_count":0,"favourites_count":0,"followers_count":0,"friends_count":0,"has_custom_timelines":false,"is_translator":false,"listed_count":0,"location":"Bayonet Point","media_count":0,"name":"Merva Sensoy","normal_followers_count":0,"pinned_tweet_ids_str":[],"possibly_sensitive":false,"profile_banner_url":"https://pbs.twimg.com/profile_banners/1909274236759506944/1746112755","profile_image_url_https":"https://pbs.twimg.com/profile_images/1917950342982987777/wwJGACeI_normal.jpg","profile_interstitial_type":"","screen_name":"sensoy21893","statuses_count":3,"translator_type":"none","url":"https://t.co/I70fRK6vA5","verified":false,"want_retweets":false,"withheld_in_countries":[]},"smart_blocked_by":false,"smart_blocking":false,"business_account":{}}}},"unmention_data":{},"edit_control":{"edit_tweet_ids":["1926800646226784509"],"editable_until_msecs":"1748223646000","is_edit_eligible":false,"edits_remaining":"5"},"is_translatable":false,"views":{"count":"8","state":"EnabledWithCount"},"source":"<a href=\"https://mobile.twitter.com\" rel=\"nofollow\">Twitter Web App</a>","legacy":{"created_at":"Mon May 26 00:40:46 +0000 2025","conversation_id_str":"1926790701271982290","display_text_range":[11,79],"entities":{"user_mentions":[{"id_str":"48111864","name":"Alec Stapp","screen_name":"AlecStapp","indices":[0,10]},{"id_str":"1471078735","name":"Lawrence Fuller","screen_name":"Analyst_Fuller","indices":[62,77]}],"urls":[],"hashtags":[],"symbols":[]},"favorite_count":0,"favorited":false,"full_text":"@AlecStapp This guy has great tweets and excellent analysis🎉\n(@Analyst_Fuller)🔥","in_reply_to_screen_name":"AlecStapp","in_reply_to_status_id_str":"1926790701271982290","in_reply_to_user_id_str":"48111864","is_quote_status":false,"lang":"en","quote_count":0,"reply_count":0,"retweet_count":0,"retweeted":false,"user_id_str":"1909274236759506944","id_str":"1926800646226784509"},"quick_promote_eligibility":{"eligibility":"IneligibleNotProfessional"}}},"tweetDisplayType":"Tweet"},"clientEventInfo":{"component":"tweet","element":"tweet","details":{"conversationDetails":{"conversationSection":"LowQuality"},"timelinesDetails":{"controllerData":"DAACDAAEDAABCgABFICKiDADAAUKAAIAAAAABwCASAAAAAA="}}}}}],"displayType":"VerticalConversation","clientEventInfo":{"component":"tweet","element":"tweet","details":{"conversationDetails":{"conversationSection":"LowQuality"}}}}},{"entryId":"conversationthread-1926792058414551271","sortIndex":"7296581335582793427","content":{"entryType":"TimelineTimelineModule","__typename":"TimelineTimelineModule","items":[{"entryId":"conversationthread-1926792058414551271-tweet-1926792058414551271","item":{"itemContent":{"itemType":"TimelineTweet","__typename":"TimelineTweet","tweet_results":{"result":{"__typename":"Tweet","rest_id":"1926792058414551271","has_birdwatch_notes":false,"core":{"user_results":{"result":{"__typename":"User","id":"VXNlcjoxOTEwNjQ2OTQwMDcwNTM1MTY5","rest_id":"1910646940070535169","affiliates_highlighted_label":{},"has_graduated_access":true,"is_blue_verified":false,"legacy":{"can_dm":false,"can_media_tag":true,"created_at":"Fri Apr 11 10:52:17 +0000 2025","default_profile":true,"default_profile_image":false,"description":"nd beau\nGreat worry crime family science size result. Pe","entities":{"description":{"urls":[]},"url":{"urls":[{"display_url":"last.fm/user/hernandez…","expanded_url":"https://www.last.fm/user/hernandezmartha","url":"https://t.co/Wr5LMcuFGt","indices":[0,23]}]}},"fast_followers_count":0,"favourites_count":0,"followers_count":1,"friends_count":0,"has_custom_timelines":false,"is_translator":false,"listed_count":0,"location":"Gackle","media_count":0,"name":"Neptun Duran","normal_followers_count":1,"pinned_tweet_ids_str":[],"possibly_sensitive":false,"profile_banner_url":"https://pbs.twimg.com/profile_banners/1910646940070535169/1746113826","profile_image_url_https":"https://pbs.twimg.com/profile_images/1917953970162524160/NKSbdMan_normal.jpg","profile_interstitial_type":"","screen_name":"NeptunD34991","statuses_count":16,"translator_type":"none","url":"https://t.co/Wr5LMcuFGt","verified":false,"want_retweets":false,"withheld_in_countries":[]},"smart_blocked_by":false,"smart_blocking":false,"business_account":{}}}},"unmention_data":{},"edit_control":{"edit_tweet_ids":["1926792058414551271"],"editable_until_msecs":"1748221599000","is_edit_eligible":false,"edits_remaining":"5"},"is_translatable":false,"views":{"count":"18","state":"EnabledWithCount"},"source":"<a href=\"https://mobile.twitter.com\" rel=\"nofollow\">Twitter Web App</a>","legacy":{"created_at":"Mon May 26 00:06:39 +0000 2025","conversation_id_str":"1926790701271982290","display_text_range":[11,124],"entities":{"user_mentions":[{"id_str":"48111864","name":"Alec Stapp","screen_name":"AlecStapp","indices":[0,10]},{"id_str":"1433918024","name":"🇺🇸American Stock Intelligencer🇺🇸_Lucas","screen_name":"Trader__Lucas","indices":[11,25]}],"urls":[],"hashtags":[],"symbols":[]},"favorite_count":0,"favorited":false,"full_text":"@AlecStapp @Trader__Lucas A very good analyst, I admire his professional ability. After following him, my income doubled. 💦🌐","in_reply_to_screen_name":"AlecStapp","in_reply_to_status_id_str":"1926790701271982290","in_reply_to_user_id_str":"48111864","is_quote_status":false,"lang":"en","quote_count":0,"reply_count":0,"retweet_count":0,"retweeted":false,"user_id_str":"1910646940070535169","id_str":"1926792058414551271"},"quick_promote_eligibility":{"eligibility":"IneligibleNotProfessional"}}},"tweetDisplayType":"Tweet"},"clientEventInfo":{"component":"tweet","element":"tweet","details":{"conversationDetails":{"conversationSection":"LowQuality"},"timelinesDetails":{"controllerData":"DAACDAAEDAABCgABFICKiCADAAUKAAIAAAAABwCASAAAAAA="}}}}}],"displayType":"VerticalConversation","clientEventInfo":{"component":"tweet","element":"tweet","details":{"conversationDetails":{"conversationSection":"LowQuality"}}}}},{"entryId":"conversationthread-1926793976612303356","sortIndex":"7296581335582793417","content":{"entryType":"TimelineTimelineModule","__typename":"TimelineTimelineModule","items":[{"entryId":"conversationthread-1926793976612303356-tweet-1926793976612303356","item":{"itemContent":{"itemType":"TimelineTweet","__typename":"TimelineTweet","tweet_results":{"result":{"__typename":"Tweet","rest_id":"1926793976612303356","has_birdwatch_notes":false,"core":{"user_results":{"result":{"__typename":"User","id":"VXNlcjoxOTE0MTM5MDEyMjgyOTE2ODY0","rest_id":"1914139012282916864","affiliates_highlighted_label":{},"has_graduated_access":true,"is_blue_verified":false,"legacy":{"can_dm":false,"can_media_tag":true,"created_at":"Mon Apr 21 02:08:08 +0000 2025","default_profile":true,"default_profile_image":false,"description":"","entities":{"description":{"urls":[]}},"fast_followers_count":0,"favourites_count":0,"followers_count":0,"friends_count":0,"has_custom_timelines":false,"is_translator":false,"listed_count":0,"location":"","media_count":0,"name":"PatriciaWood","normal_followers_count":0,"pinned_tweet_ids_str":[],"possibly_sensitive":false,"profile_image_url_https":"https://pbs.twimg.com/profile_images/1914618060398354432/eU_rNoFq_normal.jpg","profile_interstitial_type":"","screen_name":"mikaishi1971","statuses_count":5,"translator_type":"none","verified":false,"want_retweets":false,"withheld_in_countries":[]},"smart_blocked_by":false,"smart_blocking":false,"business_account":{}}}},"unmention_data":{},"edit_control":{"edit_tweet_ids":["1926793976612303356"],"editable_until_msecs":"1748222056000","is_edit_eligible":false,"edits_remaining":"5"},"is_translatable":false,"views":{"count":"14","state":"EnabledWithCount"},"source":"<a href=\"https://mobile.twitter.com\" rel=\"nofollow\">Twitter Web App</a>","legacy":{"created_at":"Mon May 26 00:14:16 +0000 2025","conversation_id_str":"1926790701271982290","display_text_range":[11,114],"entities":{"user_mentions":[{"id_str":"48111864","name":"Alec Stapp","screen_name":"AlecStapp","indices":[0,10]},{"id_str":"48230410","name":"Isaac Nelson","screen_name":"IsaacNelsonX17","indices":[11,26]}],"urls":[],"hashtags":[],"symbols":[]},"favorite_count":0,"favorited":false,"full_text":"@AlecStapp @IsaacNelsonX17 just next level consolidation right where u said stayed disciplined crushing the market","in_reply_to_screen_name":"AlecStapp","in_reply_to_status_id_str":"1926790701271982290","in_reply_to_user_id_str":"48111864","is_quote_status":false,"lang":"en","quote_count":0,"reply_count":0,"retweet_count":0,"retweeted":false,"user_id_str":"1914139012282916864","id_str":"1926793976612303356"},"quick_promote_eligibility":{"eligibility":"IneligibleNotProfessional"}}},"tweetDisplayType":"Tweet"},"clientEventInfo":{"component":"tweet","element":"tweet","details":{"conversationDetails":{"conversationSection":"LowQuality"},"timelinesDetails":{"controllerData":"DAACDAAEDAABCgABFICKiCADAAUKAAIAAAAABQCASAAAAAA="}}}}}],"displayType":"VerticalConversation","clientEventInfo":{"component":"tweet","element":"tweet","details":{"conversationDetails":{"conversationSection":"LowQuality"}}}}},{"entryId":"cursor-showmorethreadsprompt-560242471171299970","sortIndex":"7296581335582793416","content":{"entryType":"TimelineTimelineItem","__typename":"TimelineTimelineItem","itemContent":{"itemType":"TimelineTimelineCursor","__typename":"TimelineTimelineCursor","value":"bQAAAPBeHBm21sOwzcOPkrU1nIG2yauvsr01jIK7ncyAq701zsO-3eTKq701-sO59dS-r701psS6-bfFrL019sS90fHLsr01tMa2xZyUiLs1-Me1tbi6rL01wMW6tZfxrL01joe58biBrr01JQYRFRAAAA","cursorType":"ShowMoreThreadsPrompt","displayTreatment":{"actionText":"Show","labelText":"Show additional replies, including those that may contain offensive content"}}}}]},{"type":"TimelineTerminateTimeline","direction":"Top"}]}}}